coolmysql.py
coolmysql-2.0.1.dist-info/LICENSE
coolmysql-2.0.1.dist-info/WHEEL
coolmysql-2.0.1.dist-info/METADATA
coolmysql-2.0.1.dist-info/RECORD
