Metadata-Version: 2.1
Name: coolmysql
Version: 2.0.1
Summary: 一个优雅的 mysql ORM ，无须做模型映射，所有操作都同时提供同步、异步两种方式。
Keywords: mysql,pymysql,aiomysql,orm,coolmysql
Author-email: 江南雨上 <lcctoor@outlook.com>
Classifier: License :: OSI Approved :: Apache Software License
Requires-Dist: arts>=2024.2.25
Project-URL: HomePage, https://github.com/lcctoor/arts/tree/main/arts/coolmysql
